<?xml version="1.0" encoding="utf-8"?>
<openerp>
    <data noupdate="0">
        <!-- Office -->
        <record id="office_ho" model="hr_indonesia.office">
            <field name="name">HO</field>
            <field name="code">KPST</field>
            <field name="sequence">1</field>
        </record>

        <record id="office_kbn" model="hr_indonesia.office">
            <field name="name">Kebun</field>
            <field name="code">KOKB</field>
            <field name="sequence">2</field>
        </record>
    </data>
</openerp>
